lite_mcp_client/__init__.py
lite_mcp_client/cli.py
lite_mcp_client/client.py
lite_mcp_client/config.py
lite_mcp_client/connection.py
lite_mcp_client/llm_processing.py
lite_mcp_client/main.py
lite_mcp_client/utils.py
lite_mcp_client-0.1.0.dist-info/METADATA
lite_mcp_client-0.1.0.dist-info/WHEEL
lite_mcp_client-0.1.0.dist-info/entry_points.txt
lite_mcp_client-0.1.0.dist-info/top_level.txt
lite_mcp_client-0.1.0.dist-info/RECORD
