Metadata-Version: 2.4
Name: lite-mcp-client
Version: 0.1.0
Summary: 一个基于命令行的轻量级MCP客户端
Requires-Python: >=3.11
Requires-Dist: langchain-anthropic>=0.3.10
Requires-Dist: langchain-aws>=0.2.18
Requires-Dist: langchain-google-genai>=2.1.2
Requires-Dist: langchain-openai>=0.3.11
Requires-Dist: mcp>=1.6.0
